{
  "boilerplate": "@mufan/code-boilerplates/typescript",
  "options": {
    "name": "boring-router-packages",
    "license": "MIT",
    "author": "Chengdu Mufan Technology Co., Ltd.",
    "packages": [
      {
        "name": "boring-router",
        "projects": [
          {
            "name": "library",
            "module": ["cjs", "esm"]
          },
          {
            "name": "test"
          }
        ]
      },
      {
        "name": "boring-router-react",
        "projects": [
          {
            "name": "library",
            "module": ["cjs", "esm"],
            "references": [
              {
                "package": "boring-router",
                "project": "library"
              }
            ]
          }
        ]
      },
      {
        "name": "@boring-router-examples/basic",
        "dir": "examples/basic",
        "projects": [
          {
            "dir": false,
            "src": false,
            "references": [
              {
                "package": "boring-router",
                "project": "library"
              },
              {
                "package": "boring-router-react",
                "project": "library"
              }
            ]
          }
        ]
      },
      {
        "name": "@boring-router-examples/lifecycle-hooks",
        "dir": "examples/lifecycle-hooks",
        "projects": [
          {
            "dir": false,
            "src": false,
            "references": [
              {
                "package": "boring-router",
                "project": "library"
              },
              {
                "package": "boring-router-react",
                "project": "library"
              }
            ]
          }
        ]
      },
      {
        "name": "@boring-router-examples/parallel-routes",
        "dir": "examples/parallel-routes",
        "projects": [
          {
            "dir": false,
            "src": false,
            "references": [
              {
                "package": "boring-router",
                "project": "library"
              },
              {
                "package": "boring-router-react",
                "project": "library"
              }
            ]
          }
        ]
      },
      {
        "name": "@boring-router-examples/route-content",
        "dir": "examples/route-content",
        "projects": [
          {
            "dir": false,
            "src": false,
            "references": [
              {
                "package": "boring-router",
                "project": "library"
              },
              {
                "package": "boring-router-react",
                "project": "library"
              }
            ]
          }
        ]
      }
    ]
  }
}
